[
  {
    "kode": "1117062001",
    "nama": "Blang Paku"
  },
  {
    "kode": "1117062004",
    "nama": "Pante Raya"
  },
  {
    "kode": "1117062005",
    "nama": "Simpang Balek"
  },
  {
    "kode": "1117062006",
    "nama": "Simpang Teritit"
  },
  {
    "kode": "1117062007",
    "nama": "Suka Jadi"
  },
  {
    "kode": "1117062008",
    "nama": "Suka Makmur"
  },
  {
    "kode": "1117062009",
    "nama": "Suka Ramai Atas"
  },
  {
    "kode": "1117062010",
    "nama": "Suka Ramai Bawah"
  },
  {
    "kode": "1117062011",
    "nama": "Syura Jadi"
  },
  {
    "kode": "1117062012",
    "nama": "Jamur Uluh"
  },
  {
    "kode": "1117062013",
    "nama": "Gegerung"
  },
  {
    "kode": "1117062014",
    "nama": "Merie Satu"
  },
  {
    "kode": "1117062015",
    "nama": "Blang Benara"
  },
  {
    "kode": "1117062016",
    "nama": "Bukit Pepanyi"
  },
  {
    "kode": "1117062017",
    "nama": "Wih Pesam"
  },
  {
    "kode": "1117062018",
    "nama": "Cinta Damai"
  },
  {
    "kode": "1117062019",
    "nama": "Bener Ayu"
  },
  {
    "kode": "1117062020",
    "nama": "Bener Mulie"
  },
  {
    "kode": "1117062021",
    "nama": "Blang Kucak"
  },
  {
    "kode": "1117062022",
    "nama": "Wonosobo"
  },
  {
    "kode": "1117062023",
    "nama": "Lut Kucak"
  },
  {
    "kode": "1117062024",
    "nama": "Kebun Baru"
  },
  {
    "kode": "1117062025",
    "nama": "Simpang Antara"
  },
  {
    "kode": "1117062026",
    "nama": "Jamur Ujung"
  },
  {
    "kode": "1117062027",
    "nama": "Suka Makmur Timur"
  },
  {
    "kode": "1117062028",
    "nama": "Burni Telong"
  }
]