[
  {
    "kode": "1202152001",
    "nama": "Hutanagodang"
  },
  {
    "kode": "1202152002",
    "nama": "Unte Mungkur"
  },
  {
    "kode": "1202152003",
    "nama": "Hutalontung"
  },
  {
    "kode": "1202152004",
    "nama": "Hutaginjang"
  },
  {
    "kode": "1202152005",
    "nama": "Dolok Matumbur"
  },
  {
    "kode": "1202152006",
    "nama": "Mariba Ni Aek"
  },
  {
    "kode": "1202152007",
    "nama": "Sampuran"
  },
  {
    "kode": "1202152008",
    "nama": "Silando"
  },
  {
    "kode": "1202152009",
    "nama": "Sibandang"
  },
  {
    "kode": "1202152010",
    "nama": "Simatupang"
  },
  {
    "kode": "1202152011",
    "nama": "Silali Toruan"
  },
  {
    "kode": "1202152012",
    "nama": "Batubinumbun"
  },
  {
    "kode": "1202152013",
    "nama": "Sitanggor"
  },
  {
    "kode": "1202152014",
    "nama": "Papande"
  },
  {
    "kode": "1202152015",
    "nama": "Aritonang"
  }
]