[
  {
    "kode": "1205151009",
    "nama": "Beras Basah"
  },
  {
    "kode": "1205151010",
    "nama": "Bukit Jengkol"
  },
  {
    "kode": "1205152001",
    "nama": "Alur Cempedak"
  },
  {
    "kode": "1205152002",
    "nama": "Sei Siur"
  },
  {
    "kode": "1205152003",
    "nama": "Tanjung Pasar"
  },
  {
    "kode": "1205152004",
    "nama": "Paya Tampak"
  },
  {
    "kode": "1205152005",
    "nama": "Pintu Air"
  },
  {
    "kode": "1205152006",
    "nama": "Sei Meran"
  },
  {
    "kode": "1205152007",
    "nama": "Pulau Sembilan"
  },
  {
    "kode": "1205152008",
    "nama": "Pulau Kampai"
  },
  {
    "kode": "1205152011",
    "nama": "Pangkalan Siata"
  }
]