[
  {
    "kode": "1209212001",
    "nama": "Aek Songsongan"
  },
  {
    "kode": "1209212002",
    "nama": "Perkebunan Bandar Selamat"
  },
  {
    "kode": "1209212003",
    "nama": "Perkebunan Bandar Pulau"
  },
  {
    "kode": "1209212004",
    "nama": "Aek Bamban"
  },
  {
    "kode": "1209212005",
    "nama": "Marjanji Aceh"
  },
  {
    "kode": "1209212006",
    "nama": "Lobu Rappa"
  },
  {
    "kode": "1209212007",
    "nama": "Tangga"
  },
  {
    "kode": "1209212008",
    "nama": "Situnjak"
  },
  {
    "kode": "1209212009",
    "nama": "Mekar Marjanji"
  }
]