[
  {
    "kode": "1214352001",
    "nama": "Lahusa Idanotae"
  },
  {
    "kode": "1214352002",
    "nama": "Hiliserangkai"
  },
  {
    "kode": "1214352003",
    "nama": "Orahua"
  },
  {
    "kode": "1214352004",
    "nama": "Hilimbowo Idanotae"
  },
  {
    "kode": "1214352005",
    "nama": "Sirahia"
  },
  {
    "kode": "1214352006",
    "nama": "Umbu Idanotae"
  },
  {
    "kode": "1214352007",
    "nama": "Awoni"
  },
  {
    "kode": "1214352008",
    "nama": "'Hilisalo''o'"
  },
  {
    "kode": "1214352009",
    "nama": "Balombaruzo Orahua"
  },
  {
    "kode": "1214352010",
    "nama": "Harefa Orahua"
  },
  {
    "kode": "1214352011",
    "nama": "Hiligabungan"
  },
  {
    "kode": "1214352012",
    "nama": "Buhawa"
  }
]