[
  {
    "kode": "1216092001",
    "nama": "Purba Bersatu"
  },
  {
    "kode": "1216092002",
    "nama": "Purba Baringin"
  },
  {
    "kode": "1216092003",
    "nama": "Karya"
  },
  {
    "kode": "1216092004",
    "nama": "Manalu"
  },
  {
    "kode": "1216092005",
    "nama": "Sijarango"
  },
  {
    "kode": "1216092006",
    "nama": "Tukka Dolok"
  },
  {
    "kode": "1216092007",
    "nama": "Siambaton"
  },
  {
    "kode": "1216092008",
    "nama": "Parmonangan"
  },
  {
    "kode": "1216092009",
    "nama": "Sipagabu"
  },
  {
    "kode": "1216092010",
    "nama": "Banuarea"
  },
  {
    "kode": "1216092011",
    "nama": "Rura Tanjung"
  },
  {
    "kode": "1216092012",
    "nama": "Rura Aek Sopang"
  },
  {
    "kode": "1216092013",
    "nama": "Lumban Tonga-Tonga"
  },
  {
    "kode": "1216092014",
    "nama": "Pulo Godang"
  },
  {
    "kode": "1216092015",
    "nama": "Pakkat Hauagong"
  },
  {
    "kode": "1216092016",
    "nama": "Peadungdung"
  },
  {
    "kode": "1216092017",
    "nama": "Sijarango I"
  },
  {
    "kode": "1216092018",
    "nama": "Ambobi Paranginan"
  },
  {
    "kode": "1216092019",
    "nama": "Purba Sianjur"
  },
  {
    "kode": "1216092020",
    "nama": "Siambaton Pahae"
  },
  {
    "kode": "1216092021",
    "nama": "Panggugunan"
  },
  {
    "kode": "1216092022",
    "nama": "Hauagong"
  }
]