[
  {
    "kode": "1277041001",
    "nama": "Hutaimbaru"
  },
  {
    "kode": "1277041002",
    "nama": "Lubuk Raya"
  },
  {
    "kode": "1277041003",
    "nama": "Sabungan Jae"
  },
  {
    "kode": "1277041004",
    "nama": "Lembah Lubuk Manik"
  },
  {
    "kode": "1277041005",
    "nama": "Palopat Maria"
  },
  {
    "kode": "1277042006",
    "nama": "Sabungan Sipabangun"
  },
  {
    "kode": "1277042007",
    "nama": "Singali"
  },
  {
    "kode": "1277042008",
    "nama": "Huta Padang"
  },
  {
    "kode": "1277042009",
    "nama": "Partihaman Saroha"
  },
  {
    "kode": "1277042010",
    "nama": "Tinjoman Lama"
  }
]