[
  {
    "kode": "1301062005",
    "nama": "Koto Berapak"
  },
  {
    "kode": "1301062006",
    "nama": "Talaok"
  },
  {
    "kode": "1301062007",
    "nama": "Pasar Baru"
  },
  {
    "kode": "1301062008",
    "nama": "Gurun Panjang"
  },
  {
    "kode": "1301062009",
    "nama": "Api-api Pasar Baru"
  },
  {
    "kode": "1301062010",
    "nama": "Tanjung Durian Pasar Baru"
  },
  {
    "kode": "1301062011",
    "nama": "Asam Kamba Pasar Baru"
  },
  {
    "kode": "1301062012",
    "nama": "Sawah Laweh Pasar Baru"
  },
  {
    "kode": "1301062013",
    "nama": "Kapeh Panji Jaya Talaok"
  },
  {
    "kode": "1301062014",
    "nama": "Aur Begalung Talaok"
  },
  {
    "kode": "1301062015",
    "nama": "Kapelgam Koto Berapak"
  },
  {
    "kode": "1301062016",
    "nama": "Koto Baru Koto Berapak"
  },
  {
    "kode": "1301062017",
    "nama": "Kubang Koto Berapak"
  },
  {
    "kode": "1301062018",
    "nama": "Kapujan Koto Berapak"
  },
  {
    "kode": "1301062019",
    "nama": "Gurun Panjang Utara"
  },
  {
    "kode": "1301062020",
    "nama": "Gurun Panjang Barat"
  },
  {
    "kode": "1301062021",
    "nama": "Gurun Panjang Selatan"
  }
]