[
  {
    "kode": "1301102001",
    "nama": "Lunang"
  },
  {
    "kode": "1301102003",
    "nama": "Lunang Utara"
  },
  {
    "kode": "1301102004",
    "nama": "Lunang Selatan"
  },
  {
    "kode": "1301102005",
    "nama": "Lunang Barat"
  },
  {
    "kode": "1301102015",
    "nama": "Sindang Lunang"
  },
  {
    "kode": "1301102016",
    "nama": "Pondok Parian Lunang"
  },
  {
    "kode": "1301102017",
    "nama": "Lunang Tengah"
  },
  {
    "kode": "1301102018",
    "nama": "Lunang Satu"
  },
  {
    "kode": "1301102019",
    "nama": "Lunang Dua"
  },
  {
    "kode": "1301102020",
    "nama": "Lunang Tiga"
  }
]