[
  {
    "kode": "1405061001",
    "nama": "Pelalawan"
  },
  {
    "kode": "1405062002",
    "nama": "Sungai Ara"
  },
  {
    "kode": "1405062003",
    "nama": "Ransang"
  },
  {
    "kode": "1405062004",
    "nama": "Kuala Tolam"
  },
  {
    "kode": "1405062005",
    "nama": "Sering"
  },
  {
    "kode": "1405062006",
    "nama": "Telayap"
  },
  {
    "kode": "1405062007",
    "nama": "Batang Nilo Kecil"
  },
  {
    "kode": "1405062008",
    "nama": "Delik"
  },
  {
    "kode": "1405062010",
    "nama": "Lalang Kabung"
  }
]