[
  {
    "kode": "1503112001",
    "nama": "Sekamis"
  },
  {
    "kode": "1503112002",
    "nama": "Guruh Baru"
  },
  {
    "kode": "1503112003",
    "nama": "Petiduran Baru"
  },
  {
    "kode": "1503112004",
    "nama": "Sungai Butang"
  },
  {
    "kode": "1503112005",
    "nama": "Butang Baru"
  },
  {
    "kode": "1503112006",
    "nama": "Suka Maju"
  },
  {
    "kode": "1503112007",
    "nama": "Jati Baru"
  },
  {
    "kode": "1503112008",
    "nama": "Jati Baru Mudo"
  },
  {
    "kode": "1503112009",
    "nama": "Meranti Baru"
  },
  {
    "kode": "1503112010",
    "nama": "Meranti Jaya"
  },
  {
    "kode": "1503112011",
    "nama": "Jernang Baru"
  }
]