[
  {
    "kode": "1602232001",
    "nama": "Benawa"
  },
  {
    "kode": "1602232002",
    "nama": "Serapek"
  },
  {
    "kode": "1602232003",
    "nama": "Sugih Waras"
  },
  {
    "kode": "1602232004",
    "nama": "Muara Telang"
  },
  {
    "kode": "1602232005",
    "nama": "Kuripan"
  },
  {
    "kode": "1602232006",
    "nama": "Cinta Marga"
  },
  {
    "kode": "1602232007",
    "nama": "Penyandingan"
  },
  {
    "kode": "1602232008",
    "nama": "Talang Pengeran"
  },
  {
    "kode": "1602232009",
    "nama": "Ulak Ketapang"
  },
  {
    "kode": "1602232010",
    "nama": "Mulyaguna"
  },
  {
    "kode": "1602232011",
    "nama": "Panca Tunggal Benawa"
  },
  {
    "kode": "1602232012",
    "nama": "Bumi Harapan"
  },
  {
    "kode": "1602232013",
    "nama": "Sinar Harapan Mulya"
  },
  {
    "kode": "1602232014",
    "nama": "Seriguna"
  }
]