[
  {
    "kode": "1604162001",
    "nama": "Pandan Arang"
  },
  {
    "kode": "1604162002",
    "nama": "Tanjung Kurung"
  },
  {
    "kode": "1604162003",
    "nama": "Nanjungan"
  },
  {
    "kode": "1604162004",
    "nama": "Pagardin"
  },
  {
    "kode": "1604162005",
    "nama": "Pulau Beringin"
  },
  {
    "kode": "1604162006",
    "nama": "Beriningin Jaya"
  },
  {
    "kode": "1604162007",
    "nama": "Banu Ayu"
  },
  {
    "kode": "1604162008",
    "nama": "Tanjung Alam"
  },
  {
    "kode": "1604162009",
    "nama": "Sirah Pulau"
  },
  {
    "kode": "1604162010",
    "nama": "Tanjung Beringin"
  },
  {
    "kode": "1604162011",
    "nama": "Pagar Jati"
  },
  {
    "kode": "1604162012",
    "nama": "Karang Cahaya"
  },
  {
    "kode": "1604162013",
    "nama": "Jaga Baya"
  },
  {
    "kode": "1604162014",
    "nama": "Keban Agung"
  },
  {
    "kode": "1604162015",
    "nama": "Padang Bindu"
  },
  {
    "kode": "1604162016",
    "nama": "Beringin Janggut"
  },
  {
    "kode": "1604162017",
    "nama": "Keban Raya"
  },
  {
    "kode": "1604162018",
    "nama": "Lubuk Tungkang"
  }
]