[
  {
    "kode": "1609132001",
    "nama": "Sukajaya"
  },
  {
    "kode": "1609132002",
    "nama": "Kota Batu"
  },
  {
    "kode": "1609132003",
    "nama": "Pagar Dewa"
  },
  {
    "kode": "1609132004",
    "nama": "Tanjung Jati"
  },
  {
    "kode": "1609132005",
    "nama": "Gunung Aji"
  },
  {
    "kode": "1609132006",
    "nama": "Pilla"
  },
  {
    "kode": "1609132007",
    "nama": "Gunung Raya"
  },
  {
    "kode": "1609132008",
    "nama": "Remanam Jaya"
  },
  {
    "kode": "1609132009",
    "nama": "Kiwis Raya"
  },
  {
    "kode": "1609132010",
    "nama": "Segigok Raya"
  },
  {
    "kode": "1609132011",
    "nama": "Bumi Agung"
  },
  {
    "kode": "1609132012",
    "nama": "Mekar Sari"
  },
  {
    "kode": "1609132013",
    "nama": "Bedeng Tiga"
  },
  {
    "kode": "1609132014",
    "nama": "Gedung Ranau"
  },
  {
    "kode": "1609132015",
    "nama": "Tanjung Baru"
  },
  {
    "kode": "1609132016",
    "nama": "Way Wangi Seminung"
  }
]