[
  {
    "kode": "1611072001",
    "nama": "Talang Padang"
  },
  {
    "kode": "1611072002",
    "nama": "Tanjung Beringin"
  },
  {
    "kode": "1611072003",
    "nama": "Penantian"
  },
  {
    "kode": "1611072004",
    "nama": "Pagar Jati"
  },
  {
    "kode": "1611072005",
    "nama": "Kebon Jati"
  },
  {
    "kode": "1611072006",
    "nama": "Bandar Agung"
  },
  {
    "kode": "1611072007",
    "nama": "Lawang Agung"
  },
  {
    "kode": "1611072008",
    "nama": "Nanjungan"
  },
  {
    "kode": "1611072009",
    "nama": "Talang Randai"
  },
  {
    "kode": "1611072010",
    "nama": "Air Mayam"
  },
  {
    "kode": "1611072011",
    "nama": "Muara Rungga"
  },
  {
    "kode": "1611072012",
    "nama": "Padang Gelai"
  },
  {
    "kode": "1611072013",
    "nama": "Padang Bindu"
  },
  {
    "kode": "1611072014",
    "nama": "Muara Sindang"
  },
  {
    "kode": "1611072015",
    "nama": "Muara Aman"
  }
]