[
  {
    "kode": "1612022001",
    "nama": "Sukarami"
  },
  {
    "kode": "1612022002",
    "nama": "Tanjung Baru"
  },
  {
    "kode": "1612022003",
    "nama": "Prabu Menang"
  },
  {
    "kode": "1612022004",
    "nama": "Tanding Marga"
  },
  {
    "kode": "1612022005",
    "nama": "Karang Tanding"
  },
  {
    "kode": "1612022006",
    "nama": "Lubuk Tampui"
  },
  {
    "kode": "1612022007",
    "nama": "Tempirai"
  },
  {
    "kode": "1612022008",
    "nama": "Tempirai Selatan"
  },
  {
    "kode": "1612022009",
    "nama": "Kota Baru"
  },
  {
    "kode": "1612022010",
    "nama": "Tempirai Utara"
  },
  {
    "kode": "1612022011",
    "nama": "Tempirai Timur"
  },
  {
    "kode": "1612022012",
    "nama": "Tambak"
  },
  {
    "kode": "1612022013",
    "nama": "Muara Ikan"
  }
]