[
  {
    "kode": "167101",
    "nama": "Ilir Barat II"
  },
  {
    "kode": "167102",
    "nama": "Seberang Ulu I"
  },
  {
    "kode": "167103",
    "nama": "Seberang Ulu II"
  },
  {
    "kode": "167104",
    "nama": "Ilir Barat I"
  },
  {
    "kode": "167105",
    "nama": "Ilir Timur I"
  },
  {
    "kode": "167106",
    "nama": "Ilir Timur II"
  },
  {
    "kode": "167107",
    "nama": "Sukarami"
  },
  {
    "kode": "167108",
    "nama": "Sako"
  },
  {
    "kode": "167109",
    "nama": "Kemuning"
  },
  {
    "kode": "167110",
    "nama": "Kalidoni"
  },
  {
    "kode": "167111",
    "nama": "Bukit Kecil"
  },
  {
    "kode": "167112",
    "nama": "Gandus"
  },
  {
    "kode": "167113",
    "nama": "Kertapati"
  },
  {
    "kode": "167114",
    "nama": "Plaju"
  },
  {
    "kode": "167115",
    "nama": "Alang-alang Lebar"
  },
  {
    "kode": "167116",
    "nama": "Sematang Borang"
  },
  {
    "kode": "167117",
    "nama": "Jakabaring"
  },
  {
    "kode": "167118",
    "nama": "Ilir Timur Tiga"
  }
]