[
  {
    "kode": "1708041003",
    "nama": "Pensiunan"
  },
  {
    "kode": "1708041004",
    "nama": "Pasar Kepahiangan"
  },
  {
    "kode": "1708041005",
    "nama": "Pasar Ujung"
  },
  {
    "kode": "1708041011",
    "nama": "Dusun Kepahiang"
  },
  {
    "kode": "1708041025",
    "nama": "Kampung Pensiunan"
  },
  {
    "kode": "1708041026",
    "nama": "Pasar Sejantung"
  },
  {
    "kode": "1708041027",
    "nama": "Padang Lekat"
  },
  {
    "kode": "1708042001",
    "nama": "Kelilik"
  },
  {
    "kode": "1708042002",
    "nama": "Tebat Monok"
  },
  {
    "kode": "1708042006",
    "nama": "Permu"
  },
  {
    "kode": "1708042007",
    "nama": "Imigrasi Permu"
  },
  {
    "kode": "1708042008",
    "nama": "Karang Endah"
  },
  {
    "kode": "1708042009",
    "nama": "Westkust"
  },
  {
    "kode": "1708042010",
    "nama": "Kampung Bogor"
  },
  {
    "kode": "1708042012",
    "nama": "Kuto Rejo"
  },
  {
    "kode": "1708042013",
    "nama": "Karang Anyar"
  },
  {
    "kode": "1708042014",
    "nama": "Taba Tebelet"
  },
  {
    "kode": "1708042015",
    "nama": "Pelangkian"
  },
  {
    "kode": "1708042016",
    "nama": "Kelobak"
  },
  {
    "kode": "1708042017",
    "nama": "Pagar Gunung"
  },
  {
    "kode": "1708042023",
    "nama": "Sukamerindu"
  },
  {
    "kode": "1708042028",
    "nama": "Bogor Baru"
  },
  {
    "kode": "1708042029",
    "nama": "Permu bawah"
  }
]