[
  {
    "kode": "1709012001",
    "nama": "Taba Terunjam"
  },
  {
    "kode": "1709012002",
    "nama": "Talang Empat"
  },
  {
    "kode": "1709012003",
    "nama": "Padang Tambak"
  },
  {
    "kode": "1709012004",
    "nama": "Durian Demang"
  },
  {
    "kode": "1709012005",
    "nama": "Pelajau"
  },
  {
    "kode": "1709012007",
    "nama": "Dusun Baru II"
  },
  {
    "kode": "1709012008",
    "nama": "Penanding"
  },
  {
    "kode": "1709012009",
    "nama": "Karang Tinggi"
  },
  {
    "kode": "1709012010",
    "nama": "Renah Lebar"
  },
  {
    "kode": "1709012011",
    "nama": "Kancing"
  },
  {
    "kode": "1709012012",
    "nama": "Ujung Karang"
  },
  {
    "kode": "1709012013",
    "nama": "Taba Mutung"
  },
  {
    "kode": "1709012015",
    "nama": "Renah Semanek"
  }
]