[
  {
    "kode": "3204252001",
    "nama": "Cicalengka Kulon"
  },
  {
    "kode": "3204252002",
    "nama": "Cicalengka Wetan"
  },
  {
    "kode": "3204252003",
    "nama": "Babakan Peuteuy"
  },
  {
    "kode": "3204252004",
    "nama": "Cikuya"
  },
  {
    "kode": "3204252005",
    "nama": "Dampit"
  },
  {
    "kode": "3204252006",
    "nama": "Margaasih"
  },
  {
    "kode": "3204252007",
    "nama": "Narawita"
  },
  {
    "kode": "3204252008",
    "nama": "Panenjoan"
  },
  {
    "kode": "3204252009",
    "nama": "Tanjungwangi"
  },
  {
    "kode": "3204252010",
    "nama": "Tenjolaya"
  },
  {
    "kode": "3204252011",
    "nama": "Waluya"
  },
  {
    "kode": "3204252012",
    "nama": "Nagrog"
  }
]