[
  {
    "kode": "3207322001",
    "nama": "Baregbeg"
  },
  {
    "kode": "3207322002",
    "nama": "Sukamaju"
  },
  {
    "kode": "3207322003",
    "nama": "Mekarjaya"
  },
  {
    "kode": "3207322004",
    "nama": "Saguling"
  },
  {
    "kode": "3207322005",
    "nama": "Petirhilir"
  },
  {
    "kode": "3207322006",
    "nama": "Pusakanagara"
  },
  {
    "kode": "3207322007",
    "nama": "Jelat"
  },
  {
    "kode": "3207322008",
    "nama": "Karangampel"
  },
  {
    "kode": "3207322009",
    "nama": "Sukamulya"
  }
]