[
  {
    "kode": "3207172006",
    "nama": "Sidaharja"
  },
  {
    "kode": "3207172007",
    "nama": "Kertajaya"
  },
  {
    "kode": "3207172009",
    "nama": "Sukanagara"
  },
  {
    "kode": "3207172010",
    "nama": "Cintajaya"
  },
  {
    "kode": "3207172011",
    "nama": "Cintaratu"
  },
  {
    "kode": "3207172012",
    "nama": "Sindangangin"
  },
  {
    "kode": "3207172013",
    "nama": "Tambakreja"
  },
  {
    "kode": "3207172017",
    "nama": "Baregbeg"
  },
  {
    "kode": "3207172018",
    "nama": "Kalapasawit"
  },
  {
    "kode": "3207172019",
    "nama": "Puloerang"
  }
]