[
  {
    "kode": "3208232001",
    "nama": "Garatengah"
  },
  {
    "kode": "3208232002",
    "nama": "Rajadanu"
  },
  {
    "kode": "3208232003",
    "nama": "Singkup"
  },
  {
    "kode": "3208232004",
    "nama": "Japara"
  },
  {
    "kode": "3208232005",
    "nama": "Wano"
  },
  {
    "kode": "3208232006",
    "nama": "Citapen"
  },
  {
    "kode": "3208232007",
    "nama": "Cengal"
  },
  {
    "kode": "3208232008",
    "nama": "Cikeleng"
  },
  {
    "kode": "3208232009",
    "nama": "Kalimati"
  },
  {
    "kode": "3208232010",
    "nama": "Dukuhdalem"
  }
]