[
  {
    "kode": "3213172001",
    "nama": "Sumurbarang"
  },
  {
    "kode": "3213172002",
    "nama": "Cibogo"
  },
  {
    "kode": "3213172003",
    "nama": "Cinangsi"
  },
  {
    "kode": "3213172004",
    "nama": "Padaasih"
  },
  {
    "kode": "3213172005",
    "nama": "Sadawarna"
  },
  {
    "kode": "3213172006",
    "nama": "Majasari"
  },
  {
    "kode": "3213172007",
    "nama": "Cisaga"
  },
  {
    "kode": "3213172008",
    "nama": "Belendung"
  },
  {
    "kode": "3213172009",
    "nama": "Cibalandong Jaya"
  }
]