[
  {
    "kode": "3301082001",
    "nama": "Tritih Wetan"
  },
  {
    "kode": "3301082002",
    "nama": "Sumingkir"
  },
  {
    "kode": "3301082003",
    "nama": "Jeruklegi Wetan"
  },
  {
    "kode": "3301082004",
    "nama": "Brebeg"
  },
  {
    "kode": "3301082005",
    "nama": "Jeruklegi Kulon"
  },
  {
    "kode": "3301082006",
    "nama": "Cilibang"
  },
  {
    "kode": "3301082007",
    "nama": "Mandala"
  },
  {
    "kode": "3301082008",
    "nama": "Karangkemiri"
  },
  {
    "kode": "3301082009",
    "nama": "Jambusari"
  },
  {
    "kode": "3301082010",
    "nama": "Prapagan"
  },
  {
    "kode": "3301082011",
    "nama": "Sawangan"
  },
  {
    "kode": "3301082012",
    "nama": "Citepus"
  },
  {
    "kode": "3301082013",
    "nama": "Tritih Lor"
  }
]