[
  {
    "kode": "3308162001",
    "nama": "Pakis"
  },
  {
    "kode": "3308162002",
    "nama": "Banyusidi"
  },
  {
    "kode": "3308162003",
    "nama": "Losari"
  },
  {
    "kode": "3308162004",
    "nama": "Daseh"
  },
  {
    "kode": "3308162005",
    "nama": "Gumelem"
  },
  {
    "kode": "3308162006",
    "nama": "Kaponan"
  },
  {
    "kode": "3308162007",
    "nama": "Kragilan"
  },
  {
    "kode": "3308162008",
    "nama": "Ketundan"
  },
  {
    "kode": "3308162009",
    "nama": "Daleman Kidul"
  },
  {
    "kode": "3308162010",
    "nama": "Petung"
  },
  {
    "kode": "3308162011",
    "nama": "Bawang"
  },
  {
    "kode": "3308162012",
    "nama": "Rejosari"
  },
  {
    "kode": "3308162013",
    "nama": "Kajangkoso"
  },
  {
    "kode": "3308162014",
    "nama": "Munengwarangan"
  },
  {
    "kode": "3308162015",
    "nama": "Gondangsari"
  },
  {
    "kode": "3308162016",
    "nama": "Kenalan"
  },
  {
    "kode": "3308162017",
    "nama": "Pogalan"
  },
  {
    "kode": "3308162018",
    "nama": "Gejagan"
  },
  {
    "kode": "3308162019",
    "nama": "Muneng"
  },
  {
    "kode": "3308162020",
    "nama": "Jambewangi"
  }
]