[
  {
    "kode": "3314112001",
    "nama": "Bentak"
  },
  {
    "kode": "3314112002",
    "nama": "Purwosuman"
  },
  {
    "kode": "3314112003",
    "nama": "Patihan"
  },
  {
    "kode": "3314112004",
    "nama": "Duyungan"
  },
  {
    "kode": "3314112005",
    "nama": "Jetak"
  },
  {
    "kode": "3314112006",
    "nama": "Sidoharjo"
  },
  {
    "kode": "3314112007",
    "nama": "Singopadu"
  },
  {
    "kode": "3314112008",
    "nama": "Taraman"
  },
  {
    "kode": "3314112009",
    "nama": "Tenggak"
  },
  {
    "kode": "3314112010",
    "nama": "Sribit"
  },
  {
    "kode": "3314112011",
    "nama": "Jambanan"
  },
  {
    "kode": "3314112012",
    "nama": "Pandak"
  }
]