[
  {
    "kode": "3318122001",
    "nama": "Jambean Kidul"
  },
  {
    "kode": "3318122002",
    "nama": "Wangunrejo"
  },
  {
    "kode": "3318122003",
    "nama": "Bumirejo"
  },
  {
    "kode": "3318122004",
    "nama": "Sokokulon"
  },
  {
    "kode": "3318122005",
    "nama": "Jimbaran"
  },
  {
    "kode": "3318122006",
    "nama": "Ngawen"
  },
  {
    "kode": "3318122007",
    "nama": "Margorejo"
  },
  {
    "kode": "3318122008",
    "nama": "Penambuhan"
  },
  {
    "kode": "3318122009",
    "nama": "Langenharjo"
  },
  {
    "kode": "3318122010",
    "nama": "Dadirejo"
  },
  {
    "kode": "3318122011",
    "nama": "Sukoharjo"
  },
  {
    "kode": "3318122012",
    "nama": "Badegan"
  },
  {
    "kode": "3318122013",
    "nama": "Pegandan"
  },
  {
    "kode": "3318122014",
    "nama": "Sokobubuk"
  },
  {
    "kode": "3318122015",
    "nama": "Banyuurip"
  },
  {
    "kode": "3318122016",
    "nama": "Mataraman"
  },
  {
    "kode": "3318122017",
    "nama": "Langse"
  },
  {
    "kode": "3318122018",
    "nama": "Muktiharjo"
  }
]