[
  {
    "kode": "3323072001",
    "nama": "Kedu"
  },
  {
    "kode": "3323072002",
    "nama": "Candimulyo"
  },
  {
    "kode": "3323072003",
    "nama": "Salamsari"
  },
  {
    "kode": "3323072004",
    "nama": "Danurejo"
  },
  {
    "kode": "3323072005",
    "nama": "Mojotengah"
  },
  {
    "kode": "3323072006",
    "nama": "Karangtejo"
  },
  {
    "kode": "3323072007",
    "nama": "Mergowati"
  },
  {
    "kode": "3323072008",
    "nama": "Kutoanyar"
  },
  {
    "kode": "3323072009",
    "nama": "Kundisari"
  },
  {
    "kode": "3323072010",
    "nama": "Ngadimulyo"
  },
  {
    "kode": "3323072011",
    "nama": "Gondangwayang"
  },
  {
    "kode": "3323072012",
    "nama": "Bojonegoro"
  },
  {
    "kode": "3323072013",
    "nama": "Bandunggede"
  },
  {
    "kode": "3323072014",
    "nama": "Tegalsari"
  }
]