[
  {
    "kode": "3323081001",
    "nama": "Parakan Wetan"
  },
  {
    "kode": "3323081006",
    "nama": "Parakan Kauman"
  },
  {
    "kode": "3323082002",
    "nama": "Campursalam"
  },
  {
    "kode": "3323082003",
    "nama": "Wanutengah"
  },
  {
    "kode": "3323082004",
    "nama": "Nglondong"
  },
  {
    "kode": "3323082005",
    "nama": "Bagusan"
  },
  {
    "kode": "3323082007",
    "nama": "Dangkel"
  },
  {
    "kode": "3323082008",
    "nama": "Mandisari"
  },
  {
    "kode": "3323082009",
    "nama": "Tegalroso"
  },
  {
    "kode": "3323082010",
    "nama": "Traji"
  },
  {
    "kode": "3323082011",
    "nama": "Watukumpul"
  },
  {
    "kode": "3323082012",
    "nama": "Ringinanom"
  },
  {
    "kode": "3323082013",
    "nama": "Depokharjo"
  },
  {
    "kode": "3323082014",
    "nama": "Caturanom"
  },
  {
    "kode": "3323082015",
    "nama": "Glapansari"
  },
  {
    "kode": "3323082016",
    "nama": "Sunggingsari"
  }
]