[
  {
    "kode": "3325062002",
    "nama": "Sendang"
  },
  {
    "kode": "3325062003",
    "nama": "Banteng"
  },
  {
    "kode": "3325062004",
    "nama": "Sumurbanger"
  },
  {
    "kode": "3325062005",
    "nama": "Margosono"
  },
  {
    "kode": "3325062006",
    "nama": "Sidalang"
  },
  {
    "kode": "3325062007",
    "nama": "Plosowangi"
  },
  {
    "kode": "3325062008",
    "nama": "Wanar"
  },
  {
    "kode": "3325062009",
    "nama": "Gondo"
  },
  {
    "kode": "3325062010",
    "nama": "Rejosari Barat"
  },
  {
    "kode": "3325062011",
    "nama": "Boja"
  },
  {
    "kode": "3325062012",
    "nama": "Pujut"
  },
  {
    "kode": "3325062013",
    "nama": "Tersono"
  },
  {
    "kode": "3325062014",
    "nama": "Tanjungsari"
  },
  {
    "kode": "3325062015",
    "nama": "Kebumen"
  },
  {
    "kode": "3325062016",
    "nama": "Harjowinangun Barat"
  },
  {
    "kode": "3325062017",
    "nama": "Tegalombo"
  },
  {
    "kode": "3325062020",
    "nama": "Kranggan"
  },
  {
    "kode": "3325062021",
    "nama": "Satriyan"
  },
  {
    "kode": "3325062022",
    "nama": "Harjowinangun Timur"
  },
  {
    "kode": "3325062023",
    "nama": "Rejosari Timur"
  }
]