[
  {
    "kode": "3504082001",
    "nama": "Bungur"
  },
  {
    "kode": "3504082002",
    "nama": "Babadan"
  },
  {
    "kode": "3504082003",
    "nama": "Sukowiyono"
  },
  {
    "kode": "3504082004",
    "nama": "Sembon"
  },
  {
    "kode": "3504082005",
    "nama": "Sukowidodo"
  },
  {
    "kode": "3504082006",
    "nama": "Tanjungsari"
  },
  {
    "kode": "3504082007",
    "nama": "Gedangan"
  },
  {
    "kode": "3504082008",
    "nama": "Sukodono"
  },
  {
    "kode": "3504082009",
    "nama": "Karangrejo"
  },
  {
    "kode": "3504082010",
    "nama": "Sukorejo"
  },
  {
    "kode": "3504082011",
    "nama": "Punjul"
  },
  {
    "kode": "3504082012",
    "nama": "Jeli"
  },
  {
    "kode": "3504082013",
    "nama": "Tulungrejo"
  }
]