[
  {
    "kode": "3504182001",
    "nama": "Sambitan"
  },
  {
    "kode": "3504182002",
    "nama": "Bono"
  },
  {
    "kode": "3504182003",
    "nama": "Sukoanyar"
  },
  {
    "kode": "3504182004",
    "nama": "Duwet"
  },
  {
    "kode": "3504182005",
    "nama": "Tamban"
  },
  {
    "kode": "3504182006",
    "nama": "Ngebong"
  },
  {
    "kode": "3504182007",
    "nama": "Sodo"
  },
  {
    "kode": "3504182008",
    "nama": "Gombang"
  },
  {
    "kode": "3504182009",
    "nama": "Pakel"
  },
  {
    "kode": "3504182010",
    "nama": "Suwaluh"
  },
  {
    "kode": "3504182011",
    "nama": "Pecuk"
  },
  {
    "kode": "3504182012",
    "nama": "Bangunmulyo"
  },
  {
    "kode": "3504182013",
    "nama": "Kasreman"
  },
  {
    "kode": "3504182014",
    "nama": "Sanan"
  },
  {
    "kode": "3504182015",
    "nama": "Bangunjaya"
  },
  {
    "kode": "3504182016",
    "nama": "Ngrance"
  },
  {
    "kode": "3504182017",
    "nama": "Gebang"
  },
  {
    "kode": "3504182018",
    "nama": "Gesikan"
  },
  {
    "kode": "3504182019",
    "nama": "Gempolan"
  }
]