[
  {
    "kode": "3507042001",
    "nama": "Tambakasri"
  },
  {
    "kode": "3507042002",
    "nama": "Tegalrejo"
  },
  {
    "kode": "3507042003",
    "nama": "Sekarbanyu"
  },
  {
    "kode": "3507042004",
    "nama": "Klepu"
  },
  {
    "kode": "3507042005",
    "nama": "Ringinkembar"
  },
  {
    "kode": "3507042006",
    "nama": "Kedungbanteng"
  },
  {
    "kode": "3507042007",
    "nama": "Sitiarjo"
  },
  {
    "kode": "3507042008",
    "nama": "Sumberagung"
  },
  {
    "kode": "3507042009",
    "nama": "Argotirto"
  },
  {
    "kode": "3507042010",
    "nama": "Harjokuncaran"
  },
  {
    "kode": "3507042011",
    "nama": "Sumbermanjing Wetan"
  },
  {
    "kode": "3507042012",
    "nama": "Ringinsari"
  },
  {
    "kode": "3507042013",
    "nama": "Druju"
  },
  {
    "kode": "3507042014",
    "nama": "Tambakrejo"
  },
  {
    "kode": "3507042015",
    "nama": "Sidoasri"
  }
]