[
  {
    "kode": "3513052001",
    "nama": "Malasankulon"
  },
  {
    "kode": "3513052002",
    "nama": "Tigasan Wetan"
  },
  {
    "kode": "3513052003",
    "nama": "Tigasan Kulon"
  },
  {
    "kode": "3513052004",
    "nama": "Pondok Wuluh"
  },
  {
    "kode": "3513052005",
    "nama": "Leces"
  },
  {
    "kode": "3513052006",
    "nama": "Sumberkedawung"
  },
  {
    "kode": "3513052007",
    "nama": "Kerpangan"
  },
  {
    "kode": "3513052008",
    "nama": "Clarak"
  },
  {
    "kode": "3513052009",
    "nama": "Jorongan"
  },
  {
    "kode": "3513052010",
    "nama": "Warujinggo"
  }
]