[
  {
    "kode": "3524152001",
    "nama": "Dadapan"
  },
  {
    "kode": "3524152002",
    "nama": "Tebluru"
  },
  {
    "kode": "3524152003",
    "nama": "Sugihan"
  },
  {
    "kode": "3524152004",
    "nama": "Tenggulun"
  },
  {
    "kode": "3524152005",
    "nama": "Payaman"
  },
  {
    "kode": "3524152006",
    "nama": "Solokuro"
  },
  {
    "kode": "3524152007",
    "nama": "Takerharjo"
  },
  {
    "kode": "3524152008",
    "nama": "Dagan"
  },
  {
    "kode": "3524152009",
    "nama": "Banyubang"
  },
  {
    "kode": "3524152010",
    "nama": "Bluri"
  }
]