[
  {
    "kode": "3524122001",
    "nama": "Sidobogem"
  },
  {
    "kode": "3524122002",
    "nama": "Kalitengah"
  },
  {
    "kode": "3524122003",
    "nama": "Kedungdadi"
  },
  {
    "kode": "3524122004",
    "nama": "Sidorejo"
  },
  {
    "kode": "3524122005",
    "nama": "Kedungbanjar"
  },
  {
    "kode": "3524122006",
    "nama": "Bedingin"
  },
  {
    "kode": "3524122007",
    "nama": "Bakalrejo"
  },
  {
    "kode": "3524122008",
    "nama": "Gondanglor"
  },
  {
    "kode": "3524122009",
    "nama": "Pangkatrejo"
  },
  {
    "kode": "3524122010",
    "nama": "Karangsambigalih"
  },
  {
    "kode": "3524122011",
    "nama": "Supenuh"
  },
  {
    "kode": "3524122012",
    "nama": "Lebakadi"
  },
  {
    "kode": "3524122013",
    "nama": "Deketagung"
  },
  {
    "kode": "3524122014",
    "nama": "Jubellor"
  },
  {
    "kode": "3524122015",
    "nama": "Sugio"
  },
  {
    "kode": "3524122016",
    "nama": "Daliwangun"
  },
  {
    "kode": "3524122017",
    "nama": "Jubelkidul"
  },
  {
    "kode": "3524122018",
    "nama": "Lawanganagung"
  },
  {
    "kode": "3524122019",
    "nama": "Kalipang"
  },
  {
    "kode": "3524122020",
    "nama": "German"
  },
  {
    "kode": "3524122021",
    "nama": "Sekarbagus"
  }
]