[
  {
    "kode": "3525172001",
    "nama": "Dekatagung"
  },
  {
    "kode": "3525172002",
    "nama": "Kumalasa"
  },
  {
    "kode": "3525172003",
    "nama": "Suwari"
  },
  {
    "kode": "3525172004",
    "nama": "Pudakitbarat"
  },
  {
    "kode": "3525172005",
    "nama": "Pudakittimur"
  },
  {
    "kode": "3525172006",
    "nama": "Lebak"
  },
  {
    "kode": "3525172007",
    "nama": "Bululanjang"
  },
  {
    "kode": "3525172008",
    "nama": "Patarselamat"
  },
  {
    "kode": "3525172009",
    "nama": "Kotakusuma"
  },
  {
    "kode": "3525172010",
    "nama": "Sungaiteluk"
  },
  {
    "kode": "3525172011",
    "nama": "Gunungteguh"
  },
  {
    "kode": "3525172012",
    "nama": "Sawahmulya"
  },
  {
    "kode": "3525172013",
    "nama": "Sungairujing"
  },
  {
    "kode": "3525172014",
    "nama": "Balikterus"
  },
  {
    "kode": "3525172015",
    "nama": "Kebontelukdalam"
  },
  {
    "kode": "3525172016",
    "nama": "Sidogedungbatu"
  },
  {
    "kode": "3525172017",
    "nama": "Daun"
  }
]