[
  {
    "kode": "3526142001",
    "nama": "Soket Laok"
  },
  {
    "kode": "3526142002",
    "nama": "Soket Dajah"
  },
  {
    "kode": "3526142003",
    "nama": "Pamorah"
  },
  {
    "kode": "3526142004",
    "nama": "Banyubeseh"
  },
  {
    "kode": "3526142005",
    "nama": "Pocong"
  },
  {
    "kode": "3526142006",
    "nama": "Tragah"
  },
  {
    "kode": "3526142007",
    "nama": "Karang Leman"
  },
  {
    "kode": "3526142008",
    "nama": "Duko Tambin"
  },
  {
    "kode": "3526142009",
    "nama": "Keteleng"
  },
  {
    "kode": "3526142010",
    "nama": "Alang Alang"
  },
  {
    "kode": "3526142011",
    "nama": "Kemoning"
  },
  {
    "kode": "3526142012",
    "nama": "Tambin"
  },
  {
    "kode": "3526142013",
    "nama": "Bajeman"
  },
  {
    "kode": "3526142014",
    "nama": "Jaddung"
  },
  {
    "kode": "3526142015",
    "nama": "Pacangan"
  },
  {
    "kode": "3526142016",
    "nama": "Bancang"
  },
  {
    "kode": "3526142017",
    "nama": "Jaah"
  },
  {
    "kode": "3526142018",
    "nama": "Masaran"
  }
]