[
  {
    "kode": "3526132001",
    "nama": "Tanah Merah Dajah"
  },
  {
    "kode": "3526132002",
    "nama": "Tanah Merah Laok"
  },
  {
    "kode": "3526132003",
    "nama": "Petrah"
  },
  {
    "kode": "3526132004",
    "nama": "Jangkar"
  },
  {
    "kode": "3526132005",
    "nama": "Pettong"
  },
  {
    "kode": "3526132006",
    "nama": "Kendaban"
  },
  {
    "kode": "3526132007",
    "nama": "Dumajah"
  },
  {
    "kode": "3526132008",
    "nama": "Pacentan"
  },
  {
    "kode": "3526132009",
    "nama": "Baipajung"
  },
  {
    "kode": "3526132010",
    "nama": "Tlomar"
  },
  {
    "kode": "3526132011",
    "nama": "Rongdurin"
  },
  {
    "kode": "3526132012",
    "nama": "Landak"
  },
  {
    "kode": "3526132013",
    "nama": "Basanah"
  },
  {
    "kode": "3526132014",
    "nama": "Poter"
  },
  {
    "kode": "3526132015",
    "nama": "Patemon"
  },
  {
    "kode": "3526132016",
    "nama": "Dlambah Dajah"
  },
  {
    "kode": "3526132017",
    "nama": "Dlambah Laok"
  },
  {
    "kode": "3526132018",
    "nama": "Mrecah"
  },
  {
    "kode": "3526132019",
    "nama": "Buddan"
  },
  {
    "kode": "3526132020",
    "nama": "Batangan"
  },
  {
    "kode": "3526132021",
    "nama": "Padurungan"
  },
  {
    "kode": "3526132022",
    "nama": "Pangeleyan"
  },
  {
    "kode": "3526132023",
    "nama": "Kranggan Barat"
  }
]