[
  {
    "kode": "3601042001",
    "nama": "Tanjungan"
  },
  {
    "kode": "3601042002",
    "nama": "Sumurbatu"
  },
  {
    "kode": "3601042003",
    "nama": "Sukawaris"
  },
  {
    "kode": "3601042004",
    "nama": "Rancaseneng"
  },
  {
    "kode": "3601042005",
    "nama": "Parungkokosan"
  },
  {
    "kode": "3601042006",
    "nama": "Nanggala"
  },
  {
    "kode": "3601042007",
    "nama": "Cikeusik"
  },
  {
    "kode": "3601042008",
    "nama": "Cikadongdong"
  },
  {
    "kode": "3601042009",
    "nama": "Curugciung"
  },
  {
    "kode": "3601042010",
    "nama": "Leuwibalang"
  },
  {
    "kode": "3601042011",
    "nama": "Sukaseneng"
  },
  {
    "kode": "3601042012",
    "nama": "Sukamulya"
  },
  {
    "kode": "3601042013",
    "nama": "Umbulan"
  },
  {
    "kode": "3601042014",
    "nama": "Cikiruhwetan"
  }
]