[
  {
    "kode": "3604262001",
    "nama": "Jawilan"
  },
  {
    "kode": "3604262002",
    "nama": "Bojot"
  },
  {
    "kode": "3604262003",
    "nama": "Cemplang"
  },
  {
    "kode": "3604262004",
    "nama": "Pagintungan"
  },
  {
    "kode": "3604262005",
    "nama": "Pasirbuyut"
  },
  {
    "kode": "3604262006",
    "nama": "Majasari"
  },
  {
    "kode": "3604262007",
    "nama": "Parakan"
  },
  {
    "kode": "3604262008",
    "nama": "Kareo"
  },
  {
    "kode": "3604262009",
    "nama": "Junti"
  }
]