[
  {
    "kode": "5201032001",
    "nama": "Lembuak"
  },
  {
    "kode": "5201032002",
    "nama": "Nyur Lembang"
  },
  {
    "kode": "5201032003",
    "nama": "Peresak"
  },
  {
    "kode": "5201032004",
    "nama": "Keru"
  },
  {
    "kode": "5201032005",
    "nama": "Batu Kuta"
  },
  {
    "kode": "5201032006",
    "nama": "Tanak Beak"
  },
  {
    "kode": "5201032007",
    "nama": "Sedau"
  },
  {
    "kode": "5201032008",
    "nama": "Suranadi"
  },
  {
    "kode": "5201032009",
    "nama": "Selat"
  },
  {
    "kode": "5201032010",
    "nama": "Lebah Sempage"
  },
  {
    "kode": "5201032011",
    "nama": "Sesaot"
  },
  {
    "kode": "5201032012",
    "nama": "Dasan Tereng"
  },
  {
    "kode": "5201032013",
    "nama": "Badrain"
  },
  {
    "kode": "5201032014",
    "nama": "Sembung"
  },
  {
    "kode": "5201032015",
    "nama": "Kramat Jaya"
  },
  {
    "kode": "5201032016",
    "nama": "Grimax Indah"
  },
  {
    "kode": "5201032017",
    "nama": "Pakuan"
  },
  {
    "kode": "5201032018",
    "nama": "Golong"
  },
  {
    "kode": "5201032019",
    "nama": "Mekarsari"
  },
  {
    "kode": "5201032020",
    "nama": "Buwun Sejati"
  },
  {
    "kode": "5201032021",
    "nama": "Narmada"
  }
]