[
  {
    "kode": "5307082001",
    "nama": "Darat Gunung"
  },
  {
    "kode": "5307082002",
    "nama": "Ojang"
  },
  {
    "kode": "5307082003",
    "nama": "Hikong"
  },
  {
    "kode": "5307082006",
    "nama": "Nebe"
  },
  {
    "kode": "5307082007",
    "nama": "Wailamung"
  },
  {
    "kode": "5307082008",
    "nama": "Lewomada"
  },
  {
    "kode": "5307082010",
    "nama": "Nangahale"
  },
  {
    "kode": "5307082011",
    "nama": "Darat Pantai"
  },
  {
    "kode": "5307082013",
    "nama": "Talibura"
  },
  {
    "kode": "5307082014",
    "nama": "Kringa"
  },
  {
    "kode": "5307082015",
    "nama": "Bangkoor"
  },
  {
    "kode": "5307082017",
    "nama": "Timutawa"
  },
  {
    "kode": "5307082019",
    "nama": "Udek Du’en"
  },
  {
    "kode": "5307082020",
    "nama": "Watu Omok"
  },
  {
    "kode": "5307082021",
    "nama": "Waipaar"
  },
  {
    "kode": "5307082022",
    "nama": "Baokremot"
  },
  {
    "kode": "5307082023",
    "nama": "Henga"
  },
  {
    "kode": "5307082024",
    "nama": "Likonggete"
  },
  {
    "kode": "5307082025",
    "nama": "Watubaing"
  },
  {
    "kode": "5307082026",
    "nama": "Mamai"
  }
]