[
  {
    "kode": "5315042001",
    "nama": "Golo Ndaring"
  },
  {
    "kode": "5315042005",
    "nama": "Golo Kempo"
  },
  {
    "kode": "5315042008",
    "nama": "Golo Manting"
  },
  {
    "kode": "5315042009",
    "nama": "Matawae"
  },
  {
    "kode": "5315042011",
    "nama": "Nampar Macing"
  },
  {
    "kode": "5315042014",
    "nama": "Wae Sano"
  },
  {
    "kode": "5315042016",
    "nama": "Golo Mbu"
  },
  {
    "kode": "5315042017",
    "nama": "Golo Leleng"
  },
  {
    "kode": "5315042018",
    "nama": "Sano Nggoang"
  },
  {
    "kode": "5315042020",
    "nama": "Wae Lolos"
  },
  {
    "kode": "5315042024",
    "nama": "Golo Sengang"
  },
  {
    "kode": "5315042025",
    "nama": "Watu Panggal"
  },
  {
    "kode": "5315042026",
    "nama": "Golo Kondeng"
  },
  {
    "kode": "5315042027",
    "nama": "Poco Golo Kempo"
  },
  {
    "kode": "5315042028",
    "nama": "Pulau Nuncung"
  }
]