[
  {
    "kode": "6101012001",
    "nama": "Dalam Kaum"
  },
  {
    "kode": "6101012002",
    "nama": "Lubuk Dagang"
  },
  {
    "kode": "6101012003",
    "nama": "Tanjung Bugis"
  },
  {
    "kode": "6101012004",
    "nama": "Pendawan"
  },
  {
    "kode": "6101012005",
    "nama": "Pasar Melayu"
  },
  {
    "kode": "6101012006",
    "nama": "Durian"
  },
  {
    "kode": "6101012007",
    "nama": "Lorong"
  },
  {
    "kode": "6101012008",
    "nama": "Jagur"
  },
  {
    "kode": "6101012009",
    "nama": "Tumuk Manggis"
  },
  {
    "kode": "6101012010",
    "nama": "Tanjung Mekar"
  },
  {
    "kode": "6101012011",
    "nama": "Sebayan"
  },
  {
    "kode": "6101012012",
    "nama": "Kartiasa"
  },
  {
    "kode": "6101012013",
    "nama": "Saing Rambi"
  },
  {
    "kode": "6101012014",
    "nama": "Lumbang"
  },
  {
    "kode": "6101012015",
    "nama": "Sungai Rambah"
  },
  {
    "kode": "6101012023",
    "nama": "Gapura"
  },
  {
    "kode": "6101012024",
    "nama": "Sumber Harapan"
  },
  {
    "kode": "6101012029",
    "nama": "Semangau"
  }
]