[
  {
    "kode": "6105022001",
    "nama": "Nanga Tempunak"
  },
  {
    "kode": "6105022002",
    "nama": "Mensiap Baru"
  },
  {
    "kode": "6105022003",
    "nama": "Tanjung Perada"
  },
  {
    "kode": "6105022004",
    "nama": "Suka Jaya"
  },
  {
    "kode": "6105022005",
    "nama": "Mengkurat Baru"
  },
  {
    "kode": "6105022006",
    "nama": "Peribang Baru"
  },
  {
    "kode": "6105022007",
    "nama": "Repak Sari"
  },
  {
    "kode": "6105022008",
    "nama": "Pagal Baru"
  },
  {
    "kode": "6105022009",
    "nama": "Kenyabur Baru"
  },
  {
    "kode": "6105022010",
    "nama": "Benua Baru"
  },
  {
    "kode": "6105022011",
    "nama": "Tinum Baru"
  },
  {
    "kode": "6105022012",
    "nama": "Pangkal Baru"
  },
  {
    "kode": "6105022013",
    "nama": "Pulau Jaya"
  },
  {
    "kode": "6105022014",
    "nama": "Kuala Tiga"
  },
  {
    "kode": "6105022015",
    "nama": "Gurung Mali"
  },
  {
    "kode": "6105022016",
    "nama": "Merti Jaya"
  },
  {
    "kode": "6105022017",
    "nama": "Benua Kencana"
  },
  {
    "kode": "6105022018",
    "nama": "Balai Harapan"
  },
  {
    "kode": "6105022019",
    "nama": "Tempunak Kapuas"
  },
  {
    "kode": "6105022020",
    "nama": "Riam Batu"
  },
  {
    "kode": "6105022021",
    "nama": "Pudau Bersatu"
  },
  {
    "kode": "6105022022",
    "nama": "Kupan Jaya"
  },
  {
    "kode": "6105022023",
    "nama": "Sungai Buluh"
  },
  {
    "kode": "6105022024",
    "nama": "Jaya Mentari"
  },
  {
    "kode": "6105022025",
    "nama": "Pekulai Bersatu"
  },
  {
    "kode": "6105022026",
    "nama": "Mensiap Jaya"
  }
]