[
  {
    "kode": "6205022001",
    "nama": "Malungai"
  },
  {
    "kode": "6205022002",
    "nama": "Rarawa"
  },
  {
    "kode": "6205022003",
    "nama": "Ketapang"
  },
  {
    "kode": "6205022004",
    "nama": "Walur"
  },
  {
    "kode": "6205022005",
    "nama": "Baliti"
  },
  {
    "kode": "6205022006",
    "nama": "Majangkan"
  },
  {
    "kode": "6205022007",
    "nama": "Kandui"
  },
  {
    "kode": "6205022008",
    "nama": "Payang Ara"
  },
  {
    "kode": "6205022009",
    "nama": "Jaman"
  },
  {
    "kode": "6205022010",
    "nama": "Pelari"
  },
  {
    "kode": "6205022011",
    "nama": "Sangkorang"
  },
  {
    "kode": "6205022012",
    "nama": "Siwau"
  },
  {
    "kode": "6205022013",
    "nama": "Tongka"
  },
  {
    "kode": "6205022014",
    "nama": "Batu Raya I"
  },
  {
    "kode": "6205022015",
    "nama": "Batu Raya II"
  },
  {
    "kode": "6205022016",
    "nama": "Tapen Raya"
  }
]