[
  {
    "kode": "6501072001",
    "nama": "Lepak Aru"
  },
  {
    "kode": "6501072002",
    "nama": "Long Lasan"
  },
  {
    "kode": "6501072003",
    "nama": "Long Peso"
  },
  {
    "kode": "6501072004",
    "nama": "Long Bia"
  },
  {
    "kode": "6501072005",
    "nama": "Muara Pangean"
  },
  {
    "kode": "6501072006",
    "nama": "Long Lian"
  },
  {
    "kode": "6501072007",
    "nama": "Long Pelaah"
  },
  {
    "kode": "6501072008",
    "nama": "Long Lejuh"
  },
  {
    "kode": "6501072009",
    "nama": "Long Pelban"
  },
  {
    "kode": "6501072010",
    "nama": "Long Buang"
  }
]