[
  {
    "kode": "7110042001",
    "nama": "Modayag"
  },
  {
    "kode": "7110042002",
    "nama": "Liberia"
  },
  {
    "kode": "7110042003",
    "nama": "Purworejo"
  },
  {
    "kode": "7110042007",
    "nama": "Buyandi"
  },
  {
    "kode": "7110042008",
    "nama": "Tobongon"
  },
  {
    "kode": "7110042009",
    "nama": "Lanut"
  },
  {
    "kode": "7110042010",
    "nama": "Badaro"
  },
  {
    "kode": "7110042011",
    "nama": "Modayag Barat"
  },
  {
    "kode": "7110042012",
    "nama": "Modayag Timur"
  },
  {
    "kode": "7110042013",
    "nama": "Purworejo Timur"
  },
  {
    "kode": "7110042014",
    "nama": "Liberia Timur"
  },
  {
    "kode": "7110042016",
    "nama": "Purworejo Tengah"
  },
  {
    "kode": "7110042021",
    "nama": "Candi Rejo"
  },
  {
    "kode": "7110042022",
    "nama": "Sumber Rejo"
  }
]