[
  {
    "kode": "7207032007",
    "nama": "Sobonon"
  },
  {
    "kode": "7207032008",
    "nama": "Bolonan"
  },
  {
    "kode": "7207032009",
    "nama": "Batang Babasal"
  },
  {
    "kode": "7207032010",
    "nama": "Sampaka"
  },
  {
    "kode": "7207032011",
    "nama": "Salangano"
  },
  {
    "kode": "7207032012",
    "nama": "Sambiut"
  },
  {
    "kode": "7207032013",
    "nama": "Sakay"
  },
  {
    "kode": "7207032014",
    "nama": "Tone"
  },
  {
    "kode": "7207032015",
    "nama": "Abason"
  },
  {
    "kode": "7207032016",
    "nama": "Lopito"
  },
  {
    "kode": "7207032017",
    "nama": "Kombutokan"
  }
]