[
  {
    "kode": "7326041002",
    "nama": "'Pangala'''"
  },
  {
    "kode": "7326041004",
    "nama": "'Pangala'' Utara'"
  },
  {
    "kode": "7326042001",
    "nama": "Limbong Malting"
  },
  {
    "kode": "7326042003",
    "nama": "Rindingallo"
  },
  {
    "kode": "7326042005",
    "nama": "'Mai''ting'"
  },
  {
    "kode": "7326042006",
    "nama": "'Lo''ko'' Uru'"
  },
  {
    "kode": "7326042007",
    "nama": "Ampang Batu"
  },
  {
    "kode": "7326042008",
    "nama": "Lempo Poton"
  },
  {
    "kode": "7326042009",
    "nama": "Buntu Batu"
  }
]