[
  {
    "kode": "7371101001",
    "nama": "Barombong"
  },
  {
    "kode": "7371101002",
    "nama": "Maccini Sombala"
  },
  {
    "kode": "7371101003",
    "nama": "Jongaya"
  },
  {
    "kode": "7371101004",
    "nama": "Mangasa"
  },
  {
    "kode": "7371101005",
    "nama": "Bongaya"
  },
  {
    "kode": "7371101006",
    "nama": "Balang Baru"
  },
  {
    "kode": "7371101007",
    "nama": "Mannuruki"
  },
  {
    "kode": "7371101008",
    "nama": "'Pa''baeng-Baeng'"
  },
  {
    "kode": "7371101009",
    "nama": "Parang Tambung"
  },
  {
    "kode": "7371101010",
    "nama": "Tanjung Merdeka"
  },
  {
    "kode": "7371101011",
    "nama": "Bonto Duri"
  }
]