[
  {
    "kode": "7603112001",
    "nama": "Mokallang"
  },
  {
    "kode": "7603112002",
    "nama": "Masoso"
  },
  {
    "kode": "7603112003",
    "nama": "Saluassing"
  },
  {
    "kode": "7603112004",
    "nama": "Salubulo"
  },
  {
    "kode": "7603112005",
    "nama": "Salukadi"
  },
  {
    "kode": "7603112006",
    "nama": "Salukepopok"
  },
  {
    "kode": "7603112007",
    "nama": "Ulumambi Barat"
  },
  {
    "kode": "7603112008",
    "nama": "Limbadebata"
  },
  {
    "kode": "7603112009",
    "nama": "Tanete Tomba"
  },
  {
    "kode": "7603112010",
    "nama": "Bambang"
  },
  {
    "kode": "7603112011",
    "nama": "Rantelemo"
  },
  {
    "kode": "7603112012",
    "nama": "Saludengen"
  },
  {
    "kode": "7603112013",
    "nama": "Ulumambi"
  },
  {
    "kode": "7603112014",
    "nama": "Bambang Timur"
  },
  {
    "kode": "7603112015",
    "nama": "Minanga"
  },
  {
    "kode": "7603112016",
    "nama": "Sikamase"
  },
  {
    "kode": "7603112017",
    "nama": "Rantetarima"
  },
  {
    "kode": "7603112018",
    "nama": "Salururu"
  },
  {
    "kode": "7603112019",
    "nama": "Salutabang"
  },
  {
    "kode": "7603112020",
    "nama": "Balatana"
  }
]