[
  {
    "kode": "7604162001",
    "nama": "Bulo"
  },
  {
    "kode": "7604162002",
    "nama": "Pulliwa"
  },
  {
    "kode": "7604162003",
    "nama": "Patambanua"
  },
  {
    "kode": "7604162004",
    "nama": "Karombang"
  },
  {
    "kode": "7604162005",
    "nama": "Daala Timur"
  },
  {
    "kode": "7604162006",
    "nama": "Lenggo"
  },
  {
    "kode": "7604162007",
    "nama": "Sabura"
  },
  {
    "kode": "7604162008",
    "nama": "Sepporraki"
  },
  {
    "kode": "7604162009",
    "nama": "Ihing"
  }
]