[
  {
    "kode": "8101262001",
    "nama": "Ouw"
  },
  {
    "kode": "8101262002",
    "nama": "Ullath"
  },
  {
    "kode": "8101262003",
    "nama": "Siri Sori Islam"
  },
  {
    "kode": "8101262004",
    "nama": "Siri Sori Amalatu"
  },
  {
    "kode": "8101262005",
    "nama": "Mahu"
  },
  {
    "kode": "8101262006",
    "nama": "Tuhaha"
  },
  {
    "kode": "8101262007",
    "nama": "Ihamahu"
  },
  {
    "kode": "8101262008",
    "nama": "Iha"
  },
  {
    "kode": "8101262009",
    "nama": "Nolloth"
  },
  {
    "kode": "8101262010",
    "nama": "Itawaka"
  }
]