[
  {
    "kode": "8272061001",
    "nama": "Akelamo"
  },
  {
    "kode": "8272062002",
    "nama": "Lola"
  },
  {
    "kode": "8272062003",
    "nama": "Aketobololo"
  },
  {
    "kode": "8272062004",
    "nama": "Aketobatu"
  },
  {
    "kode": "8272062005",
    "nama": "Akedotilou"
  },
  {
    "kode": "8272062006",
    "nama": "Akeguraci"
  },
  {
    "kode": "8272062007",
    "nama": "Akesai"
  },
  {
    "kode": "8272062008",
    "nama": "Togeme"
  },
  {
    "kode": "8272062009",
    "nama": "Tadupi"
  },
  {
    "kode": "8272062010",
    "nama": "Baringin Jaya"
  },
  {
    "kode": "8272062011",
    "nama": "Tauno"
  },
  {
    "kode": "8272062012",
    "nama": "Fanaha"
  },
  {
    "kode": "8272062013",
    "nama": "Yehu"
  },
  {
    "kode": "8272062014",
    "nama": "Siokona"
  }
]