[
  {
    "kode": "9202032001",
    "nama": "Dindey"
  },
  {
    "kode": "9202032002",
    "nama": "Indisey"
  },
  {
    "kode": "9202032003",
    "nama": "Hingk"
  },
  {
    "kode": "9202032004",
    "nama": "Warmare"
  },
  {
    "kode": "9202032005",
    "nama": "Nimbay"
  },
  {
    "kode": "9202032006",
    "nama": "Meny"
  },
  {
    "kode": "9202032007",
    "nama": "Tanah Merah"
  },
  {
    "kode": "9202032008",
    "nama": "Umcen"
  },
  {
    "kode": "9202032009",
    "nama": "Subsay"
  },
  {
    "kode": "9202032010",
    "nama": "Madrat"
  },
  {
    "kode": "9202032011",
    "nama": "Snaimboy"
  },
  {
    "kode": "9202032012",
    "nama": "Guentuy"
  },
  {
    "kode": "9202032013",
    "nama": "Ngungguen"
  },
  {
    "kode": "9202032014",
    "nama": "Sotea"
  },
  {
    "kode": "9202032015",
    "nama": "Duwin"
  },
  {
    "kode": "9202032016",
    "nama": "Ibuwau"
  },
  {
    "kode": "9202032017",
    "nama": "Iboisrati"
  },
  {
    "kode": "9202032018",
    "nama": "Sraindabey"
  },
  {
    "kode": "9202032019",
    "nama": "Mokwam"
  },
  {
    "kode": "9202032020",
    "nama": "Amber"
  },
  {
    "kode": "9202032021",
    "nama": "Kwau"
  },
  {
    "kode": "9202032022",
    "nama": "Syou"
  },
  {
    "kode": "9202032023",
    "nama": "Indonbey"
  },
  {
    "kode": "9202032024",
    "nama": "Mingre"
  },
  {
    "kode": "9202032025",
    "nama": "Aiwow"
  },
  {
    "kode": "9202032026",
    "nama": "Asarbey"
  },
  {
    "kode": "9202032027",
    "nama": "Minoqbei"
  },
  {
    "kode": "9202032028",
    "nama": "Bahamyenti"
  },
  {
    "kode": "9202032029",
    "nama": "Figoud"
  },
  {
    "kode": "9202032030",
    "nama": "Kipuwau"
  },
  {
    "kode": "9202032031",
    "nama": "Duweibey"
  }
]